baderkit/__init__.py
baderkit/command_line/__init__.py
baderkit/command_line/base.py
baderkit/core/__init__.py
baderkit/core/bader.py
baderkit/core/methods/README.md
baderkit/core/methods/__init__.py
baderkit/core/methods/base.py
baderkit/core/methods/shared_numba.py
baderkit/core/methods/gradient_weight/README.md
baderkit/core/methods/gradient_weight/gradient_weight_method.py
baderkit/core/methods/gradient_weight/gradient_weight_numba.py
baderkit/core/methods/neargrid/__init__.py
baderkit/core/methods/neargrid/neargrid_method.py
baderkit/core/methods/neargrid/neargrid_numba.py
baderkit/core/methods/neargrid_old/neargrid_method.py
baderkit/core/methods/neargrid_old/neargrid_numba.py
baderkit/core/methods/neargrid_weight/__init__.py
baderkit/core/methods/neargrid_weight/neargrid_weight_method.py
baderkit/core/methods/neargrid_weight/neargrid_weight_numba.py
baderkit/core/methods/ongrid/__init__.py
baderkit/core/methods/ongrid/ongrid_method.py
baderkit/core/methods/ongrid/ongrid_numba.py
baderkit/core/methods/weight/__init__.py
baderkit/core/methods/weight/weight_method.py
baderkit/core/methods/weight/weight_numba.py
baderkit/core/toolkit/__init__.py
baderkit/core/toolkit/file_parsers.py
baderkit/core/toolkit/grid.py
baderkit/core/toolkit/grid_numba.py
baderkit/core/toolkit/structure.py
baderkit/plotting/__init__.py
baderkit/plotting/core/__init__.py
baderkit/plotting/core/defaults.py
baderkit/plotting/core/plotter.py
baderkit/plotting/gui/__init__.py
baderkit/plotting/gui/main.py
baderkit/plotting/gui/stylesheets/custom.qss
baderkit/plotting/gui/stylesheets/logo.svg
baderkit/plotting/gui/tabs/__init__.py
baderkit/plotting/gui/tabs/atom_tab.py
baderkit/plotting/gui/tabs/bader_tab.py
baderkit/plotting/gui/tabs/basin_tab.py
baderkit/plotting/gui/tabs/export_tab.py
baderkit/plotting/gui/tabs/style_tab.py
baderkit/plotting/gui/tabs/surface_tab.py
baderkit/plotting/gui/tabs/view_tab.py
baderkit/plotting/gui/widgets/__init__.py
baderkit-0.7.0.dist-info/licenses/LICENSE.txt
baderkit-0.7.0.dist-info/METADATA
baderkit-0.7.0.dist-info/WHEEL
baderkit-0.7.0.dist-info/entry_points.txt
baderkit-0.7.0.dist-info/top_level.txt
baderkit-0.7.0.dist-info/RECORD
