Metadata-Version: 2.4
Name: baderkit
Version: 0.7.0
Summary: BaderKit is a python reimplementaion of the Henkelman Group's Bader code built on numba, numpy, and pymatgen.
Author-email: "Sam M. Weaver" <sammweaver@gmail.com>
License: BSD 3-Clause License
Project-URL: repository, https://github.com/SWeav02/baderkit
Classifier: Development Status :: 3 - Alpha
Classifier: Intended Audience :: Science/Research
Classifier: License :: OSI Approved :: BSD License
Classifier: Programming Language :: Python :: 3.11
Classifier: Operating System :: OS Independent
Requires-Python: >=3.10
License-File: LICENSE.txt
Requires-Dist: numpy<3.0,>=1.26.0
Requires-Dist: pandas<3.0,>=2.1.0
Requires-Dist: pymatgen<=2025.10.7,>=2022.1.9
Requires-Dist: scipy<2.0,>=1.7.2
Requires-Dist: numba<=0.62.1,>=0.59.0
Requires-Dist: typer<=0.20.0,>=0.6.1
Requires-Dist: rich<=14.2,>=11.0
Provides-Extra: gui
Requires-Dist: pyvista<=0.46.3,>=0.44.0; extra == "gui"
Requires-Dist: pyvistaqt<=0.11.3,>=0.6.0; extra == "gui"
Requires-Dist: qtpy<3.0,>=2.0.0; extra == "gui"
Provides-Extra: dev
Requires-Dist: pyvista<=0.46.3,>=0.44.0; extra == "dev"
Requires-Dist: pyvistaqt<=0.11.3,>=0.6.0; extra == "dev"
Requires-Dist: qtpy<3.0,>=2.0.0; extra == "dev"
Requires-Dist: pytest; extra == "dev"
Requires-Dist: black; extra == "dev"
Requires-Dist: isort; extra == "dev"
Requires-Dist: mkdocs; extra == "dev"
Requires-Dist: mkdocs-material; extra == "dev"
Requires-Dist: mkdocstrings-python; extra == "dev"
Requires-Dist: h5py<4,>=3.6.0; extra == "dev"
Dynamic: license-file
